absorb/__init__.py
absorb/__main__.py
absorb/annotations.py
absorb/errors.py
absorb/py.typed
absorb/catalog/__init__.py
absorb/catalog/allium.py
absorb/catalog/bigquery.py
absorb/catalog/binance.py
absorb/catalog/blocknative.py
absorb/catalog/chains.py
absorb/catalog/coingecko.py
absorb/catalog/dune.py
absorb/catalog/fourbyte.py
absorb/catalog/fred.py
absorb/catalog/git.py
absorb/catalog/growthepie.py
absorb/catalog/kalshi.py
absorb/catalog/l2beat.py
absorb/catalog/mempool_dumpster.py
absorb/catalog/snowflake.py
absorb/catalog/sourcify.py
absorb/catalog/tic.py
absorb/catalog/vera.py
absorb/catalog/defillama/__init__.py
absorb/catalog/defillama/common.py
absorb/catalog/defillama/fees.py
absorb/catalog/defillama/stablecoins.py
absorb/catalog/defillama/tvl.py
absorb/catalog/defillama/volume.py
absorb/catalog/defillama/yields.py
absorb/catalog/xatu/__init__.py
absorb/catalog/xatu/beacon_api.py
absorb/catalog/xatu/canonical_beacon.py
absorb/catalog/xatu/canonical_execution.py
absorb/catalog/xatu/common.py
absorb/catalog/xatu/libp2p.py
absorb/catalog/xatu/mempool.py
absorb/catalog/xatu/mev_relay.py
absorb/cli/__init__.py
absorb/cli/cli_helpers.py
absorb/cli/cli_outputs.py
absorb/cli/cli_parsing.py
absorb/cli/cli_run.py
absorb/cli/cli_commands/__init__.py
absorb/cli/cli_commands/command_add.py
absorb/cli/cli_commands/command_cd.py
absorb/cli/cli_commands/command_collect.py
absorb/cli/cli_commands/command_download.py
absorb/cli/cli_commands/command_info.py
absorb/cli/cli_commands/command_ls.py
absorb/cli/cli_commands/command_new.py
absorb/cli/cli_commands/command_path.py
absorb/cli/cli_commands/command_preview.py
absorb/cli/cli_commands/command_remove.py
absorb/cli/cli_commands/command_setup.py
absorb/cli/cli_commands/command_sql.py
absorb/cli/cli_commands/command_upload.py
absorb/cli/cli_commands/command_validate.py
absorb/ops/__init__.py
absorb/ops/buckets.py
absorb/ops/catalog.py
absorb/ops/coverage.py
absorb/ops/env.py
absorb/ops/formatting.py
absorb/ops/git.py
paradigm_absorb-0.3.1.dist-info/entry_points.txt
paradigm_absorb-0.3.1.dist-info/licenses/LICENSE-APACHE
paradigm_absorb-0.3.1.dist-info/licenses/LICENSE-MIT
paradigm_absorb-0.3.1.dist-info/WHEEL
paradigm_absorb-0.3.1.dist-info/METADATA
paradigm_absorb-0.3.1.dist-info/RECORD
