Metadata-Version: 2.4
Name: paradigm_absorb
Version: 0.3.1
Summary: python interface for interacting with flashbots mempool dumpster
Requires-Python: >=3.9
Classifier: Development Status :: 4 - Beta
Classifier: Intended Audience :: Developers
Classifier: Intended Audience :: Financial and Insurance Industry
Classifier: Intended Audience :: Science/Research
Classifier: License :: OSI Approved :: Apache Software License
Classifier: License :: OSI Approved :: MIT License
Classifier: Natural Language :: English
Classifier: Operating System :: MacOS
Classifier: Operating System :: Microsoft :: Windows
Classifier: Operating System :: POSIX :: Linux
Classifier: Programming Language :: Python :: 3.7
Classifier: Programming Language :: Python :: 3.8
Classifier: Programming Language :: Python :: 3.9
Classifier: Programming Language :: Python :: 3.10
Classifier: Programming Language :: Python :: 3.11
Classifier: Programming Language :: Python :: 3.12
Classifier: Typing :: Typed
License-File: LICENSE-APACHE
License-File: LICENSE-MIT
Requires-Dist: polars >= 1.0
Requires-Dist: rclone-python>=0.1.23
Requires-Dist: requests>=2.0
Requires-Dist: rich>=13.9.4
Requires-Dist: rich_argparse >= 1.5.2
Requires-Dist: toolstr >= 0.9.11
Requires-Dist: tooltime >= 0.3.4
Requires-Dist: typing-extensions >=4.9.0 ; extra == "all"
Requires-Dist: dune-spice>=0.2.7 ; extra == "all"
Requires-Dist: google-auth>=2.40.3 ; extra == "all"
Requires-Dist: google-cloud-bigquery>=3.34.0 ; extra == "all"
Requires-Dist: google-cloud>=0.34.0 ; extra == "all"
Requires-Dist: google>=3.0.0 ; extra == "all"
Requires-Dist: nitwit>=0.1.1 ; extra == "all"
Requires-Dist: paradigm-garlic>=0.1.3 ; extra == "all"
Requires-Dist: ipython>=8.18.1 ; extra == "all"
Requires-Dist: ipdb>=0.13.13 ; extra == "all"
Requires-Dist: dune-spice>=0.2.7 ; extra == "datasources"
Requires-Dist: google-auth>=2.40.3 ; extra == "datasources"
Requires-Dist: google-cloud-bigquery>=3.34.0 ; extra == "datasources"
Requires-Dist: google-cloud>=0.34.0 ; extra == "datasources"
Requires-Dist: google>=3.0.0 ; extra == "datasources"
Requires-Dist: nitwit>=0.1.1 ; extra == "datasources"
Requires-Dist: paradigm-garlic>=0.1.3 ; extra == "datasources"
Requires-Dist: ipython>=8.18.1 ; extra == "interactive"
Requires-Dist: ipdb>=0.13.13 ; extra == "interactive"
Requires-Dist: typing-extensions >=4.9.0 ; extra == "test"
Project-URL: Documentation, https://github.com/paradigmxyz/absorb
Project-URL: Source, https://github.com/paradigmxyz/absorb
Provides-Extra: all
Provides-Extra: datasources
Provides-Extra: interactive
Provides-Extra: test
